MANIFEST.in
README.md
setup.py
adaletCleaning/__init__.py
adaletCleaning/myfunctions.py
adaletCleaning/utils.py
adaletCleaning.egg-info/PKG-INFO
adaletCleaning.egg-info/SOURCES.txt
adaletCleaning.egg-info/dependency_links.txt
adaletCleaning.egg-info/top_level.txt
adaletCleaning/resources/abbreviations.json
adaletCleaning/resources/allowedChars.txt
adaletCleaning/resources/cleaningParams.txt
adaletCleaning/resources/il_ilceler.xml
adaletCleaning/resources/punctuations.txt
adaletCleaning/resources/stopwords.txt
adaletCleaning/resources/trCharToReplace.json
tests/__init__.py
tests/test_myfunctions.py