Metadata-Version: 2.1
Name: adaletCleaning
Version: 0.1.3
Summary: Veri temizleme işlemleri içeren kütüphane
Author: Murat Tekdemir
Requires-Python: >=3.6
